{
  "version": "boxless-esg-lesson4-clip-1.0",
  "image_id": "unnamed.png",
  "query": "two people near a cart",
  "winner": {
    "box_raw": [
      248,
      0,
      329,
      153
    ],
    "bbox_narrative": [
      240,
      0,
      337,
      168
    ],
    "final_score": 0.653868627151092,
    "prob_calibrated": 0.013980300165712833,
    "abstain": true
  },
  "gate": {
    "gdino_boxes": [],
    "kept_gate_scores": [
      0.0,
      0.0,
      0.0,
      0.0,
      0.0,
      0.0,
      0.0,
      0.0,
      0.0,
      0.0,
      0.0,
      0.0,
      0.0,
      0.0,
      0.0,
      0.0,
      0.0,
      0.0,
      0.0,
      0.0,
      0.0,
      0.0,
      0.0,
      0.0,
      0.0,
      0.0,
      0.0,
      0.0,
      0.0,
      0.0,
      0.0,
      0.0,
      0.0,
      0.0,
      0.0,
      0.0,
      0.0,
      0.0,
      0.0,
      0.0,
      0.0,
      0.0,
      0.0,
      0.0,
      0.0,
      0.0,
      0.0,
      0.0,
      0.0,
      0.0,
      0.0,
      0.0,
      0.0,
      0.0,
      0.0,
      0.0,
      0.0,
      0.0,
      0.0,
      0.0,
      0.0,
      0.0,
      0.0,
      0.0,
      0.0,
      0.0,
      0.0,
      0.0,
      0.0,
      0.0,
      0.0,
      0.0,
      0.0,
      0.0,
      0.0,
      0.0,
      0.0,
      0.0,
      0.0,
      0.0
    ]
  },
  "rel": {
    "mode": "near"
  },
  "affordance": {
    "mode": "none",
    "detected": {
      "faces": 1,
      "uppers": 3,
      "fulls": 1,
      "people": 2
    }
  },
  "scores": {
    "weights": {
      "clip": 0.75,
      "gdino": 0.0,
      "rel": 0.2,
      "afford": 0.05
    },
    "topk": [
      {
        "box": [
          0,
          0,
          511,
          511
        ],
        "clip": 0.5899859070777893,
        "gdino": 0.0,
        "rel": 8.251220598178387e-05,
        "afford": 0.0,
        "final": 0.4425059327495383
      },
      {
        "box": [
          0,
          124,
          61,
          304
        ],
        "clip": 0.6032953560352325,
        "gdino": 0.0,
        "rel": 0.8990569836282809,
        "afford": 0.0,
        "final": 0.6322829137520806
      },
      {
        "box": [
          172,
          337,
          308,
          418
        ],
        "clip": 0.5882136672735214,
        "gdino": 0.0,
        "rel": 0.9588049308210691,
        "afford": 0.0,
        "final": 0.6329212366193548
      },
      {
        "box": [
          6,
          0,
          110,
          106
        ],
        "clip": 0.5813833326101303,
        "gdino": 0.0,
        "rel": 0.9976926549004878,
        "afford": 0.0,
        "final": 0.6355760304376953
      },
      {
        "box": [
          350,
          0,
          455,
          105
        ],
        "clip": 0.5949303805828094,
        "gdino": 0.0,
        "rel": 0.9847526827144427,
        "afford": 0.0,
        "final": 0.6431483219799956
      },
      {
        "box": [
          87,
          227,
          171,
          359
        ],
        "clip": 0.6000327095389366,
        "gdino": 0.0,
        "rel": 0.9649407174773429,
        "afford": 0.0,
        "final": 0.643012675649671
      },
      {
        "box": [
          0,
          276,
          511,
          511
        ],
        "clip": 0.5874618738889694,
        "gdino": 0.0,
        "rel": 0.017397258655037252,
        "afford": 0.0,
        "final": 0.4440758571477345
      },
      {
        "box": [
          260,
          0,
          511,
          448
        ],
        "clip": 0.5822797864675522,
        "gdino": 0.0,
        "rel": 0.023553335022468737,
        "afford": 0.0,
        "final": 0.4414205068551579
      },
      {
        "box": [
          25,
          144,
          390,
          448
        ],
        "clip": 0.5899475812911987,
        "gdino": 0.0,
        "rel": 0.025106041214010975,
        "afford": 0.0,
        "final": 0.44748189421120127
      },
      {
        "box": [
          27,
          0,
          462,
          253
        ],
        "clip": 0.5747765898704529,
        "gdino": 0.0,
        "rel": 0.025692635018160836,
        "afford": 0.0,
        "final": 0.4362209694064718
      },
      {
        "box": [
          0,
          157,
          511,
          365
        ],
        "clip": 0.585694395005703,
        "gdino": 0.0,
        "rel": 0.03066615810494848,
        "afford": 0.0,
        "final": 0.44540402787526695
      },
      {
        "box": [
          147,
          224,
          511,
          511
        ],
        "clip": 0.5875007808208466,
        "gdino": 0.0,
        "rel": 0.03124039125552581,
        "afford": 0.0,
        "final": 0.4468736638667401
      },
      {
        "box": [
          0,
          0,
          265,
          391
        ],
        "clip": 0.5929806679487228,
        "gdino": 0.0,
        "rel": 0.031035427576874636,
        "afford": 0.0,
        "final": 0.45094258647691704
      },
      {
        "box": [
          165,
          0,
          511,
          293
        ],
        "clip": 0.5786696374416351,
        "gdino": 0.0,
        "rel": 0.03463370548029761,
        "afford": 0.0,
        "final": 0.44092896917728586
      },
      {
        "box": [
          95,
          0,
          479,
          251
        ],
        "clip": 0.5747377872467041,
        "gdino": 0.0,
        "rel": 0.04287592713369932,
        "afford": 0.0,
        "final": 0.4396285258617679
      },
      {
        "box": [
          260,
          0,
          511,
          380
        ],
        "clip": 0.5840030461549759,
        "gdino": 0.0,
        "rel": 0.04240188446200484,
        "afford": 0.0,
        "final": 0.44648266150863286
      },
      {
        "box": [
          299,
          0,
          511,
          448
        ],
        "clip": 0.5826034098863602,
        "gdino": 0.0,
        "rel": 0.04593645659614647,
        "afford": 0.0,
        "final": 0.4461398487339994
      },
      {
        "box": [
          197,
          212,
          511,
          511
        ],
        "clip": 0.5937565863132477,
        "gdino": 0.0,
        "rel": 0.046844457504493044,
        "afford": 0.0,
        "final": 0.45468633123583435
      },
      {
        "box": [
          184,
          51,
          479,
          363
        ],
        "clip": 0.5847560614347458,
        "gdino": 0.0,
        "rel": 0.051097508615890366,
        "afford": 0.0,
        "final": 0.44878654779923743
      },
      {
        "box": [
          0,
          0,
          210,
          438
        ],
        "clip": 0.5862662345170975,
        "gdino": 0.0,
        "rel": 0.05136590327141568,
        "afford": 0.0,
        "final": 0.4499728565421062
      },
      {
        "box": [
          0,
          0,
          281,
          326
        ],
        "clip": 0.5837017223238945,
        "gdino": 0.0,
        "rel": 0.04916124320375699,
        "afford": 0.0,
        "final": 0.44760854038367226
      },
      {
        "box": [
          73,
          0,
          455,
          238
        ],
        "clip": 0.5753801465034485,
        "gdino": 0.0,
        "rel": 0.053457838589585194,
        "afford": 0.0,
        "final": 0.4422266775955034
      },
      {
        "box": [
          325,
          51,
          462,
          138
        ],
        "clip": 0.5908522456884384,
        "gdino": 0.0,
        "rel": 0.8921292843499342,
        "afford": 0.0,
        "final": 0.6215650411363156
      },
      {
        "box": [
          105,
          0,
          167,
          191
        ],
        "clip": 0.6001345291733742,
        "gdino": 0.0,
        "rel": 0.9757161111524525,
        "afford": 0.0,
        "final": 0.6452441191105212
      },
      {
        "box": [
          231,
          0,
          309,
          152
        ],
        "clip": 0.6041484773159027,
        "gdino": 0.0,
        "rel": 0.971383354549445,
        "afford": 0.0,
        "final": 0.647388028896816
      },
      {
        "box": [
          264,
          137,
          358,
          263
        ],
        "clip": 0.6017752811312675,
        "gdino": 0.0,
        "rel": 0.9610019745076189,
        "afford": 0.0,
        "final": 0.6435318557499745
      },
      {
        "box": [
          171,
          433,
          478,
          471
        ],
        "clip": 0.6019650995731354,
        "gdino": 0.0,
        "rel": 0.9723101797805275,
        "afford": 0.0,
        "final": 0.6459358606359571
      },
      {
        "box": [
          456,
          0,
          511,
          213
        ],
        "clip": 0.591498926281929,
        "gdino": 0.0,
        "rel": 0.9661480079143426,
        "afford": 0.0,
        "final": 0.6368537962943153
      },
      {
        "box": [
          185,
          221,
          352,
          291
        ],
        "clip": 0.6013798862695694,
        "gdino": 0.0,
        "rel": 0.9857549346306522,
        "afford": 0.0,
        "final": 0.6481859016283075
      },
      {
        "box": [
          402,
          314,
          511,
          421
        ],
        "clip": 0.6170069649815559,
        "gdino": 0.0,
        "rel": 0.7702568434888124,
        "afford": 0.0,
        "final": 0.6168065924339294
      },
      {
        "box": [
          405,
          401,
          511,
          511
        ],
        "clip": 0.5988796874880791,
        "gdino": 0.0,
        "rel": 0.6098814228763979,
        "afford": 0.0,
        "final": 0.571136050191339
      },
      {
        "box": [
          169,
          456,
          380,
          511
        ],
        "clip": 0.5929793864488602,
        "gdino": 0.0,
        "rel": 0.9757781474842009,
        "afford": 0.0,
        "final": 0.6398901693334853
      },
      {
        "box": [
          327,
          0,
          455,
          91
        ],
        "clip": 0.5885256975889206,
        "gdino": 0.0,
        "rel": 0.9847526827144427,
        "afford": 0.0,
        "final": 0.638344809734579
      },
      {
        "box": [
          46,
          149,
          124,
          297
        ],
        "clip": 0.6025378629565239,
        "gdino": 0.0,
        "rel": 0.9797566878023302,
        "afford": 0.0,
        "final": 0.6478547347778589
      },
      {
        "box": [
          134,
          329,
          222,
          460
        ],
        "clip": 0.6063829809427261,
        "gdino": 0.0,
        "rel": 0.7044353274439725,
        "afford": 0.0,
        "final": 0.5956743011958391
      },
      {
        "box": [
          353,
          346,
          466,
          448
        ],
        "clip": 0.5897568911314011,
        "gdino": 0.0,
        "rel": 0.7702568434888124,
        "afford": 0.0,
        "final": 0.5963690370463133
      },
      {
        "box": [
          245,
          342,
          366,
          437
        ],
        "clip": 0.5890809893608093,
        "gdino": 0.0,
        "rel": 0.9815023962631778,
        "afford": 0.0,
        "final": 0.6381112212732426
      },
      {
        "box": [
          106,
          163,
          229,
          256
        ],
        "clip": 0.5915632843971252,
        "gdino": 0.0,
        "rel": 0.8865128462976213,
        "afford": 0.0,
        "final": 0.6209750325573682
      },
      {
        "box": [
          248,
          0,
          329,
          153
        ],
        "clip": 0.6074371933937073,
        "gdino": 0.0,
        "rel": 0.9914536605290573,
        "afford": 0.0,
        "final": 0.653868627151092
      },
      {
        "box": [
          205,
          436,
          478,
          481
        ],
        "clip": 0.6005127802491188,
        "gdino": 0.0,
        "rel": 0.9723101797805275,
        "afford": 0.0,
        "final": 0.6448466211429447
      },
      {
        "box": [
          259,
          88,
          351,
          222
        ],
        "clip": 0.6003548502922058,
        "gdino": 0.0,
        "rel": 0.9748686764594293,
        "afford": 0.0,
        "final": 0.6452398730110402
      },
      {
        "box": [
          185,
          338,
          389,
          398
        ],
        "clip": 0.589693658053875,
        "gdino": 0.0,
        "rel": 0.9340752187481935,
        "afford": 0.0,
        "final": 0.629085287290045
      },
      {
        "box": [
          323,
          188,
          427,
          306
        ],
        "clip": 0.5950281322002411,
        "gdino": 0.0,
        "rel": 0.9760263322565933,
        "afford": 0.0,
        "final": 0.6414763656014995
      },
      {
        "box": [
          25,
          144,
          106,
          295
        ],
        "clip": 0.6032019406557083,
        "gdino": 0.0,
        "rel": 0.9822515088920767,
        "afford": 0.0,
        "final": 0.6488517572701966
      },
      {
        "box": [
          56,
          296,
          122,
          480
        ],
        "clip": 0.597508117556572,
        "gdino": 0.0,
        "rel": 0.5091294020848688,
        "afford": 0.0,
        "final": 0.5499569685844028
      },
      {
        "box": [
          89,
          252,
          197,
          364
        ],
        "clip": 0.6019975766539574,
        "gdino": 0.0,
        "rel": 0.9649407174773429,
        "afford": 0.0,
        "final": 0.6444863259859366
      },
      {
        "box": [
          238,
          380,
          415,
          448
        ],
        "clip": 0.5907085835933685,
        "gdino": 0.0,
        "rel": 0.9712186781351222,
        "afford": 0.0,
        "final": 0.6372751733220509
      },
      {
        "box": [
          283,
          264,
          402,
          365
        ],
        "clip": 0.5944577008485794,
        "gdino": 0.0,
        "rel": 0.8199841881731409,
        "afford": 0.0,
        "final": 0.6098401132710627
      },
      {
        "box": [
          323,
          211,
          455,
          302
        ],
        "clip": 0.5926038920879364,
        "gdino": 0.0,
        "rel": 0.9760263322565933,
        "afford": 0.0,
        "final": 0.6396581855172709
      },
      {
        "box": [
          149,
          39,
          219,
          210
        ],
        "clip": 0.6037514358758926,
        "gdino": 0.0,
        "rel": 0.9272902827274743,
        "afford": 0.0,
        "final": 0.6382716334524143
      },
      {
        "box": [
          258,
          0,
          328,
          171
        ],
        "clip": 0.6014384627342224,
        "gdino": 0.0,
        "rel": 0.9914536605290573,
        "afford": 0.0,
        "final": 0.6493695791564783
      },
      {
        "box": [
          204,
          0,
          276,
          166
        ],
        "clip": 0.5968934446573257,
        "gdino": 0.0,
        "rel": 0.9657999897385303,
        "afford": 0.0,
        "final": 0.6408300814407004
      },
      {
        "box": [
          355,
          224,
          457,
          341
        ],
        "clip": 0.5919563323259354,
        "gdino": 0.0,
        "rel": 0.9214524871065789,
        "afford": 0.0,
        "final": 0.6282577466657673
      },
      {
        "box": [
          56,
          210,
          187,
          301
        ],
        "clip": 0.5937833860516548,
        "gdino": 0.0,
        "rel": 0.993136017641337,
        "afford": 0.0,
        "final": 0.6439647430670086
      },
      {
        "box": [
          132,
          262,
          263,
          359
        ],
        "clip": 0.6010993421077728,
        "gdino": 0.0,
        "rel": 0.9740426202206315,
        "afford": 0.0,
        "final": 0.6456330306249559
      },
      {
        "box": [
          254,
          348,
          382,
          447
        ],
        "clip": 0.5863066092133522,
        "gdino": 0.0,
        "rel": 0.9815023962631778,
        "afford": 0.0,
        "final": 0.6360304361626498
      },
      {
        "box": [
          260,
          112,
          375,
          222
        ],
        "clip": 0.5851390659809113,
        "gdino": 0.0,
        "rel": 0.9748686764594293,
        "afford": 0.0,
        "final": 0.6338280347775693
      },
      {
        "box": [
          334,
          292,
          463,
          390
        ],
        "clip": 0.5896519273519516,
        "gdino": 0.0,
        "rel": 0.8158759918339352,
        "afford": 0.0,
        "final": 0.6054141438807508
      },
      {
        "box": [
          46,
          117,
          128,
          271
        ],
        "clip": 0.6029359400272369,
        "gdino": 0.0,
        "rel": 0.9694296237473514,
        "afford": 0.0,
        "final": 0.646087879769898
      },
      {
        "box": [
          31,
          66,
          125,
          200
        ],
        "clip": 0.5855025872588158,
        "gdino": 0.0,
        "rel": 0.7696041653523567,
        "afford": 0.0,
        "final": 0.5930477735145832
      },
      {
        "box": [
          27,
          0,
          108,
          155
        ],
        "clip": 0.5912560671567917,
        "gdino": 0.0,
        "rel": 0.9952429790532253,
        "afford": 0.0,
        "final": 0.6424906461782388
      },
      {
        "box": [
          0,
          156,
          52,
          396
        ],
        "clip": 0.5952714085578918,
        "gdino": 0.0,
        "rel": 0.8635928004047572,
        "afford": 0.0,
        "final": 0.6191721164993703
      },
      {
        "box": [
          215,
          0,
          276,
          205
        ],
        "clip": 0.5950808823108673,
        "gdino": 0.0,
        "rel": 0.9657999897385303,
        "afford": 0.0,
        "final": 0.6394706596808566
      },
      {
        "box": [
          398,
          212,
          511,
          323
        ],
        "clip": 0.5873497202992439,
        "gdino": 0.0,
        "rel": 0.8037426167244662,
        "afford": 0.0,
        "final": 0.6012608135693263
      },
      {
        "box": [
          158,
          129,
          274,
          237
        ],
        "clip": 0.5878135859966278,
        "gdino": 0.0,
        "rel": 0.771874603163885,
        "afford": 0.0,
        "final": 0.5952351101302479
      },
      {
        "box": [
          440,
          0,
          511,
          176
        ],
        "clip": 0.5929253771901131,
        "gdino": 0.0,
        "rel": 0.9661480079143426,
        "afford": 0.0,
        "final": 0.6379236344754533
      },
      {
        "box": [
          234,
          194,
          352,
          300
        ],
        "clip": 0.5989062339067459,
        "gdino": 0.0,
        "rel": 0.9438856269686423,
        "afford": 0.0,
        "final": 0.6379568008237879
      },
      {
        "box": [
          0,
          155,
          38,
          479
        ],
        "clip": 0.6006480604410172,
        "gdino": 0.0,
        "rel": 0.8635928004047572,
        "afford": 0.0,
        "final": 0.6232046054117143
      },
      {
        "box": [
          57,
          216,
          203,
          301
        ],
        "clip": 0.5936039835214615,
        "gdino": 0.0,
        "rel": 0.993136017641337,
        "afford": 0.0,
        "final": 0.6438301911693636
      },
      {
        "box": [
          35,
          0,
          115,
          155
        ],
        "clip": 0.5918003022670746,
        "gdino": 0.0,
        "rel": 0.9952429790532253,
        "afford": 0.0,
        "final": 0.642898822510951
      },
      {
        "box": [
          286,
          0,
          380,
          144
        ],
        "clip": 0.611289419233799,
        "gdino": 0.0,
        "rel": 0.859776158453684,
        "afford": 0.0,
        "final": 0.630422296116086
      },
      {
        "box": [
          144,
          0,
          215,
          190
        ],
        "clip": 0.6069721654057503,
        "gdino": 0.0,
        "rel": 0.9272902827274743,
        "afford": 0.0,
        "final": 0.6406871805998076
      },
      {
        "box": [
          40,
          118,
          113,
          302
        ],
        "clip": 0.6084059327840805,
        "gdino": 0.0,
        "rel": 0.9822515088920767,
        "afford": 0.0,
        "final": 0.6527547513664758
      },
      {
        "box": [
          107,
          2,
          167,
          223
        ],
        "clip": 0.5963426679372787,
        "gdino": 0.0,
        "rel": 0.9757161111524525,
        "afford": 0.0,
        "final": 0.6424002231834496
      },
      {
        "box": [
          411,
          130,
          511,
          263
        ],
        "clip": 0.5896870866417885,
        "gdino": 0.0,
        "rel": 0.9884325961977977,
        "afford": 0.0,
        "final": 0.639951834220901
      },
      {
        "box": [
          169,
          457,
          414,
          511
        ],
        "clip": 0.5900760591030121,
        "gdino": 0.0,
        "rel": 0.9757781474842009,
        "afford": 0.0,
        "final": 0.6377126738240992
      },
      {
        "box": [
          396,
          148,
          511,
          263
        ],
        "clip": 0.5895265489816666,
        "gdino": 0.0,
        "rel": 0.9884325961977977,
        "afford": 0.0,
        "final": 0.6398314309758095
      },
      {
        "box": [
          326,
          0,
          436,
          120
        ],
        "clip": 0.5858968645334244,
        "gdino": 0.0,
        "rel": 0.9740426202206315,
        "afford": 0.0,
        "final": 0.6342311724441946
      },
      {
        "box": [
          0,
          0,
          113,
          116
        ],
        "clip": 0.5870297253131866,
        "gdino": 0.0,
        "rel": 0.9976926549004878,
        "afford": 0.0,
        "final": 0.6398108249649875
      },
      {
        "box": [
          218,
          278,
          370,
          363
        ],
        "clip": 0.6019472777843475,
        "gdino": 0.0,
        "rel": 0.8224904035616417,
        "afford": 0.0,
        "final": 0.6159585390505891
      }
    ]
  },
  "proposals": {
    "after_dedupe": 454,
    "kept_for_heavy": 80
  },
  "note": "GDINO anchor expansion + area penalty + optional people-cart proximity bonus."
}